testapix/__init__.py
testapix/__main__.py
testapix/_version.py
testapix/assertions/__init__.py
testapix/assertions/response.py
testapix/auth/__init__.py
testapix/auth/base.py
testapix/auth/factory.py
testapix/auth/legacy.py
testapix/auth/personas.py
testapix/auth/providers.py
testapix/auth/session.py
testapix/cli/__init__.py
testapix/cli/commands/__init__.py
testapix/cli/commands/generate.py
testapix/cli/commands/init.py
testapix/cli/commands/interactive.py
testapix/cli/main.py
testapix/cli/template_manager.py
testapix/cli/templates/__init__.py
testapix/cli/templates/configs/base.yaml.j2
testapix/cli/templates/configs/env.example.j2
testapix/cli/templates/configs/local.yaml.j2
testapix/cli/templates/configs/pytest.ini.j2
testapix/cli/templates/configs/test.yaml.j2
testapix/cli/templates/demo/README.md.j2
testapix/cli/templates/demo/data_generator.py.j2
testapix/cli/templates/demo/test_practice_software_testing_api.py.j2
testapix/cli/templates/docs/README.md.j2
testapix/cli/templates/docs/requirements.txt.j2
testapix/cli/templates/fixtures/conftest.py.j2
testapix/cli/templates/fixtures/fixtures.py.j2
testapix/cli/templates/functional/test_template.py.j2
testapix/cli/templates/generators/data_generator.py.j2
testapix/core/__init__.py
testapix/core/batch_error_reporter.py
testapix/core/client.py
testapix/core/config.py
testapix/core/events.py
testapix/core/exceptions.py
testapix/core/logging_utils.py
testapix/core/registry.py
testapix/generators/__init__.py
testapix/generators/base.py
testapix/interactive/__init__.py
testapix/interactive/commands/__init__.py
testapix/interactive/commands/auth.py
testapix/interactive/commands/generate.py
testapix/interactive/commands/http.py
testapix/interactive/commands/registry.py
testapix/interactive/commands/response.py
testapix/interactive/commands/session.py
testapix/interactive/session/__init__.py
testapix/interactive/session/manager.py
testapix/interactive/shell.py
testapix/py.typed
testapix/validation/__init__.py
testapix-0.1.4.dist-info/LICENSE
testapix-0.1.4.dist-info/METADATA
testapix-0.1.4.dist-info/WHEEL
testapix-0.1.4.dist-info/entry_points.txt
testapix-0.1.4.dist-info/RECORD
