Metadata-Version: 2.3
Name: testapix
Version: 0.1.4
Summary: A comprehensive Python API testing framework
License: MIT
Keywords: api,testing,framework,pytest,automation,test
Author: Your Name
Author-email: your.email@example.com
Requires-Python: >=3.11,<4.0
Classifier: Development Status :: 3 - Alpha
Classifier: Framework :: Pytest
Classifier: Intended Audience :: Developers
Classifier: License :: OSI Approved :: MIT License
Classifier: Programming Language :: Python :: 3
Classifier: Programming Language :: Python :: 3.11
Classifier: Programming Language :: Python :: 3.12
Classifier: Programming Language :: Python :: 3.13
Classifier: Topic :: Software Development :: Quality Assurance
Classifier: Topic :: Software Development :: Testing
Provides-Extra: interactive
Requires-Dist: click (>=8.1.7,<9.0.0)
Requires-Dist: httpx (>=0.28.1,<0.29.0)
Requires-Dist: jinja2 (>=3.1.4,<4.0.0)
Requires-Dist: jsonschema (>=4.25.0,<5.0.0)
Requires-Dist: mimesis (>=18.0.0,<19.0.0)
Requires-Dist: prompt-toolkit (>=3.0.0,<4.0.0) ; extra == "interactive"
Requires-Dist: pydantic (>=2.7.4,<3.0.0)
Requires-Dist: pydantic-settings (>=2.3.4,<3.0.0)
Requires-Dist: pytest (>=8.2.2,<9.0.0)
Requires-Dist: pyyaml (>=6.0.1,<7.0.0)
Requires-Dist: rich (>=14.1.0,<15.0.0)
Requires-Dist: twine (>=6.1.0,<7.0.0)
Project-URL: Documentation, https://testapix.readthedocs.io
Project-URL: Homepage, https://github.com/yourusername/testapix
Project-URL: Repository, https://github.com/yourusername/testapix
